[
  {
    "date": "2016-09-08",
    "num": 1,
    "source": "Facebook"
  },
  {
    "date": "2016-09-07",
    "num": 18,
    "source": "Facebook"
  },
  {
    "date": "2016-09-06",
    "num": 3,
    "source": "Facebook"
  },
  {
    "date": "2016-09-02",
    "num": 5,
    "source": "Facebook"
  },
  {
    "date": "2016-09-01",
    "num": 2,
    "source": "Facebook"
  },
  {
    "date": "2016-08-31",
    "num": 7,
    "source": "Facebook"
  },
  {
    "date": "2016-08-30",
    "num": 1,
    "source": "Facebook"
  },
  {
    "date": "2016-08-29",
    "num": 12,
    "source": "Facebook"
  },
  {
    "date": "2016-08-27",
    "num": 2,
    "source": "Facebook"
  },
  {
    "date": "2016-08-28",
    "num": 2,
    "source": "Facebook"
  },
  {
    "date": "2016-08-26",
    "num": 4,
    "source": "Facebook"
  },
  {
    "date": "2016-08-25",
    "num": 5,
    "source": "Facebook"
  },
  {
    "date": "2016-08-24",
    "num": 8,
    "source": "Facebook"
  },
  {
    "date": "2016-08-23",
    "num": 3,
    "source": "Facebook"
  },
  {
    "date": "2016-08-22",
    "num": 11,
    "source": "Facebook"
  },
  {
    "date": "2016-08-21",
    "num": 3,
    "source": "Facebook"
  },
  {
    "date": "2016-08-19",
    "num": 4,
    "source": "Facebook"
  },
  {
    "date": "2016-08-18",
    "num": 4,
    "source": "Facebook"
  },
  {
    "date": "2016-08-17",
    "num": 4,
    "source": "Facebook"
  },
  {
    "date": "2016-08-16",
    "num": 9,
    "source": "Facebook"
  },
  {
    "date": "2016-08-15",
    "num": 11,
    "source": "Facebook"
  },
  {
    "date": "2016-08-13",
    "num": 2,
    "source": "Facebook"
  },
  {
    "date": "2016-08-12",
    "num": 3,
    "source": "Facebook"
  },
  {
    "date": "2016-08-11",
    "num": 1,
    "source": "Facebook"
  },
  {
    "date": "2016-08-10",
    "num": 12,
    "source": "Facebook"
  },
  {
    "date": "2016-08-09",
    "num": 14,
    "source": "Facebook"
  },
  {
    "date": "2016-08-08",
    "num": 9,
    "source": "Facebook"
  },
  {
    "date": "2016-08-06",
    "num": 3,
    "source": "Facebook"
  },
  {
    "date": "2016-08-07",
    "num": 1,
    "source": "Facebook"
  },
  {
    "date": "2016-08-05",
    "num": 2,
    "source": "Facebook"
  },
  {
    "date": "2016-08-04",
    "num": 2,
    "source": "Facebook"
  },
  {
    "date": "2016-08-02",
    "num": 2,
    "source": "Facebook"
  },
  {
    "date": "2016-07-30",
    "num": 3,
    "source": "Facebook"
  },
  {
    "date": "2016-07-31",
    "num": 1,
    "source": "Facebook"
  },
  {
    "date": "2016-07-28",
    "num": 1,
    "source": "Facebook"
  },
  {
    "date": "2016-07-27",
    "num": 1,
    "source": "Facebook"
  },
  {
    "date": "2016-07-26",
    "num": 1,
    "source": "Facebook"
  },
  {
    "date": "2016-07-25",
    "num": 8,
    "source": "Facebook"
  },
  {
    "date": "2016-07-24",
    "num": 5,
    "source": "Facebook"
  },
  {
    "date": "2016-07-23",
    "num": 4,
    "source": "Facebook"
  },
  {
    "date": "2016-07-22",
    "num": 2,
    "source": "Facebook"
  },
  {
    "date": "2016-07-21",
    "num": 1,
    "source": "Facebook"
  },
  {
    "date": "2016-07-20",
    "num": 31,
    "source": "Facebook"
  },
  {
    "date": "2016-07-19",
    "num": 2,
    "source": "Facebook"
  },
  {
    "date": "2016-07-18",
    "num": 5,
    "source": "Facebook"
  },
  {
    "date": "2016-07-17",
    "num": 3,
    "source": "Facebook"
  },
  {
    "date": "2016-07-16",
    "num": 3,
    "source": "Facebook"
  },
  {
    "date": "2016-07-14",
    "num": 4,
    "source": "Facebook"
  },
  {
    "date": "2016-07-15",
    "num": 2,
    "source": "Facebook"
  },
  {
    "date": "2016-07-13",
    "num": 4,
    "source": "Facebook"
  },
  {
    "date": "2016-07-12",
    "num": 2,
    "source": "Facebook"
  },
  {
    "date": "2016-07-11",
    "num": 14,
    "source": "Facebook"
  },
  {
    "date": "2016-07-10",
    "num": 2,
    "source": "Facebook"
  },
  {
    "date": "2016-07-09",
    "num": 9,
    "source": "Facebook"
  },
  {
    "date": "2016-07-08",
    "num": 10,
    "source": "Facebook"
  },
  {
    "date": "2016-07-07",
    "num": 4,
    "source": "Facebook"
  },
  {
    "date": "2016-07-06",
    "num": 9,
    "source": "Facebook"
  },
  {
    "date": "2016-07-05",
    "num": 8,
    "source": "Facebook"
  },
  {
    "date": "2016-07-04",
    "num": 2,
    "source": "Facebook"
  },
  {
    "date": "2016-07-03",
    "num": 2,
    "source": "Facebook"
  },
  {
    "date": "2016-07-02",
    "num": 1,
    "source": "Facebook"
  },
  {
    "date": "2016-07-01",
    "num": 2,
    "source": "Facebook"
  },
  {
    "date": "2016-06-29",
    "num": 6,
    "source": "Facebook"
  },
  {
    "date": "2016-06-28",
    "num": 12,
    "source": "Facebook"
  },
  {
    "date": "2016-06-27",
    "num": 8,
    "source": "Facebook"
  },
  {
    "date": "2016-06-26",
    "num": 1,
    "source": "Facebook"
  },
  {
    "date": "2016-06-25",
    "num": 2,
    "source": "Facebook"
  },
  {
    "date": "2016-06-23",
    "num": 1,
    "source": "Facebook"
  },
  {
    "date": "2016-06-22",
    "num": 6,
    "source": "Facebook"
  },
  {
    "date": "2016-06-21",
    "num": 5,
    "source": "Facebook"
  },
  {
    "date": "2016-06-20",
    "num": 7,
    "source": "Facebook"
  },
  {
    "date": "2016-06-19",
    "num": 1,
    "source": "Facebook"
  },
  {
    "date": "2016-06-18",
    "num": 1,
    "source": "Facebook"
  },
  {
    "date": "2016-06-16",
    "num": 4,
    "source": "Facebook"
  },
  {
    "date": "2016-06-17",
    "num": 2,
    "source": "Facebook"
  },
  {
    "date": "2016-06-15",
    "num": 5,
    "source": "Facebook"
  },
  {
    "date": "2016-06-14",
    "num": 1,
    "source": "Facebook"
  },
  {
    "date": "2016-06-13",
    "num": 11,
    "source": "Facebook"
  },
  {
    "date": "2016-06-12",
    "num": 2,
    "source": "Facebook"
  },
  {
    "date": "2016-06-11",
    "num": 3,
    "source": "Facebook"
  },
  {
    "date": "2016-06-10",
    "num": 3,
    "source": "Facebook"
  },
  {
    "date": "2016-06-09",
    "num": 7,
    "source": "Facebook"
  },
  {
    "date": "2016-06-08",
    "num": 4,
    "source": "Facebook"
  },
  {
    "date": "2016-06-07",
    "num": 3,
    "source": "Facebook"
  },
  {
    "date": "2016-06-06",
    "num": 10,
    "source": "Facebook"
  },
  {
    "date": "2016-06-04",
    "num": 1,
    "source": "Facebook"
  },
  {
    "date": "2016-06-05",
    "num": 1,
    "source": "Facebook"
  },
  {
    "date": "2016-06-03",
    "num": 4,
    "source": "Facebook"
  },
  {
    "date": "2016-06-02",
    "num": 4,
    "source": "Facebook"
  },
  {
    "date": "2016-06-01",
    "num": 5,
    "source": "Facebook"
  },
  {
    "date": "2016-05-31",
    "num": 15,
    "source": "Facebook"
  },
  {
    "date": "2016-05-27",
    "num": 4,
    "source": "Facebook"
  },
  {
    "date": "2016-05-28",
    "num": 5,
    "source": "Facebook"
  },
  {
    "date": "2016-05-26",
    "num": 11,
    "source": "Facebook"
  },
  {
    "date": "2016-05-29",
    "num": 1,
    "source": "Facebook"
  },
  {
    "date": "2016-05-25",
    "num": 61,
    "source": "Facebook"
  },
  {
    "date": "2016-05-06",
    "num": 4,
    "source": "Facebook"
  },
  {
    "date": "2016-05-05",
    "num": 4,
    "source": "Facebook"
  },
  {
    "date": "2016-05-08",
    "num": 1,
    "source": "Facebook"
  },
  {
    "date": "2016-05-07",
    "num": 1,
    "source": "Facebook"
  },
  {
    "date": "2016-05-04",
    "num": 4,
    "source": "Facebook"
  },
  {
    "date": "2016-05-03",
    "num": 2,
    "source": "Facebook"
  },
  {
    "date": "2016-05-17",
    "num": 1,
    "source": "Facebook"
  },
  {
    "date": "2016-05-02",
    "num": 5,
    "source": "Facebook"
  },
  {
    "date": "2016-05-01",
    "num": 3,
    "source": "Facebook"
  },
  {
    "date": "2016-04-30",
    "num": 1,
    "source": "Facebook"
  },
  {
    "date": "2016-04-29",
    "num": 2,
    "source": "Facebook"
  },
  {
    "date": "2016-04-28",
    "num": 7,
    "source": "Facebook"
  },
  {
    "date": "2016-04-27",
    "num": 1,
    "source": "Facebook"
  },
  {
    "date": "2016-04-26",
    "num": 3,
    "source": "Facebook"
  },
  {
    "date": "2016-04-25",
    "num": 8,
    "source": "Facebook"
  },
  {
    "date": "2016-04-24",
    "num": 2,
    "source": "Facebook"
  },
  {
    "date": "2016-04-23",
    "num": 2,
    "source": "Facebook"
  },
  {
    "date": "2016-04-22",
    "num": 3,
    "source": "Facebook"
  },
  {
    "date": "2016-04-21",
    "num": 3,
    "source": "Facebook"
  },
  {
    "date": "2016-05-13",
    "num": 2,
    "source": "Facebook"
  },
  {
    "date": "2016-04-20",
    "num": 3,
    "source": "Facebook"
  },
  {
    "date": "2016-04-19",
    "num": 6,
    "source": "Facebook"
  },
  {
    "date": "2016-04-18",
    "num": 10,
    "source": "Facebook"
  },
  {
    "date": "2016-04-17",
    "num": 2,
    "source": "Facebook"
  },
  {
    "date": "2016-04-15",
    "num": 4,
    "source": "Facebook"
  },
  {
    "date": "2016-04-16",
    "num": 1,
    "source": "Facebook"
  },
  {
    "date": "2016-04-14",
    "num": 4,
    "source": "Facebook"
  },
  {
    "date": "2016-04-13",
    "num": 9,
    "source": "Facebook"
  },
  {
    "date": "2016-04-11",
    "num": 7,
    "source": "Facebook"
  },
  {
    "date": "2016-04-12",
    "num": 3,
    "source": "Facebook"
  },
  {
    "date": "2016-04-10",
    "num": 3,
    "source": "Facebook"
  },
  {
    "date": "2016-04-09",
    "num": 2,
    "source": "Facebook"
  },
  {
    "date": "2016-04-08",
    "num": 6,
    "source": "Facebook"
  },
  {
    "date": "2016-04-07",
    "num": 8,
    "source": "Facebook"
  },
  {
    "date": "2016-04-06",
    "num": 1,
    "source": "Facebook"
  },
  {
    "date": "2016-04-05",
    "num": 20,
    "source": "Facebook"
  },
  {
    "date": "2016-04-03",
    "num": 2,
    "source": "Facebook"
  },
  {
    "date": "2016-04-02",
    "num": 2,
    "source": "Facebook"
  },
  {
    "date": "2016-03-31",
    "num": 2,
    "source": "Facebook"
  },
  {
    "date": "2016-04-01",
    "num": 4,
    "source": "Facebook"
  },
  {
    "date": "2016-03-30",
    "num": 14,
    "source": "Facebook"
  },
  {
    "date": "2016-03-29",
    "num": 1,
    "source": "Facebook"
  },
  {
    "date": "2016-03-28",
    "num": 10,
    "source": "Facebook"
  },
  {
    "date": "2016-03-27",
    "num": 1,
    "source": "Facebook"
  },
  {
    "date": "2016-03-26",
    "num": 1,
    "source": "Facebook"
  },
  {
    "date": "2016-03-25",
    "num": 4,
    "source": "Facebook"
  },
  {
    "date": "2016-03-24",
    "num": 2,
    "source": "Facebook"
  },
  {
    "date": "2016-03-23",
    "num": 2,
    "source": "Facebook"
  },
  {
    "date": "2016-03-22",
    "num": 15,
    "source": "Facebook"
  },
  {
    "date": "2016-03-21",
    "num": 4,
    "source": "Facebook"
  },
  {
    "date": "2016-03-18",
    "num": 5,
    "source": "Facebook"
  },
  {
    "date": "2016-03-19",
    "num": 1,
    "source": "Facebook"
  },
  {
    "date": "2016-03-17",
    "num": 6,
    "source": "Facebook"
  },
  {
    "date": "2016-03-16",
    "num": 10,
    "source": "Facebook"
  },
  {
    "date": "2016-03-11",
    "num": 2,
    "source": "Facebook"
  },
  {
    "date": "2016-03-14",
    "num": 3,
    "source": "Facebook"
  },
  {
    "date": "2016-03-09",
    "num": 4,
    "source": "Facebook"
  },
  {
    "date": "2016-03-05",
    "num": 2,
    "source": "Facebook"
  },
  {
    "date": "2016-03-06",
    "num": 3,
    "source": "Facebook"
  },
  {
    "date": "2016-03-07",
    "num": 1,
    "source": "Facebook"
  },
  {
    "date": "2016-03-03",
    "num": 1,
    "source": "Facebook"
  },
  {
    "date": "2016-03-02",
    "num": 1,
    "source": "Facebook"
  },
  {
    "date": "2016-03-01",
    "num": 6,
    "source": "Facebook"
  },
  {
    "date": "2016-02-29",
    "num": 4,
    "source": "Facebook"
  },
  {
    "date": "2016-02-28",
    "num": 1,
    "source": "Facebook"
  },
  {
    "date": "2016-02-27",
    "num": 1,
    "source": "Facebook"
  },
  {
    "date": "2016-02-26",
    "num": 2,
    "source": "Facebook"
  },
  {
    "date": "2016-02-25",
    "num": 2,
    "source": "Facebook"
  }
]